{"copyright":"Copyright 2026 MLB Advanced Media, L.P.  Use of any content on this page acknowledges agreement to the terms posted here http://gdx.mlb.com/components/copyright.txt","awards":[{"id":"SALPOWH","name":"SAL Player of the Week","date":"2013-05-13","season":"2013","team":{"id":428,"link":"/api/v1/teams/428","teamName":"Greenville"},"player":{"id":605141,"link":"/api/v1/people/605141","primaryPosition":{"code":"O","name":"Outfield","type":"Outfielder","abbreviation":"OF"}}},{"id":"SALMSAS","name":"SAL Mid-Season All-Star","date":"2013-06-01","season":"2013","team":{"id":428,"link":"/api/v1/teams/428","teamName":"Greenville"},"player":{"id":605141,"link":"/api/v1/people/605141","primaryPosition":{"code":"4","name":"Second Base","type":"Infielder","abbreviation":"2B"}}},{"id":"CARPOWH","name":"CAR Player of the Week","date":"2013-08-12","season":"2013","team":{"id":414,"link":"/api/v1/teams/414","teamName":"Salem"},"player":{"id":605141,"link":"/api/v1/people/605141","primaryPosition":{"code":"4","name":"Second Base","type":"Infielder","abbreviation":"2B"}}},{"id":"CARPOWH","name":"CAR Player of the Week","date":"2013-08-26","season":"2013","team":{"id":414,"link":"/api/v1/teams/414","teamName":"Salem"},"player":{"id":605141,"link":"/api/v1/people/605141","primaryPosition":{"code":"6","name":"Shortstop","type":"Infielder","abbreviation":"SS"}}},{"id":"MILBORGAS","name":"MiLB.com Organization All-Star","date":"2013-10-05","season":"2013","team":{"id":111,"link":"/api/v1/teams/111","teamName":"Boston"},"player":{"id":605141,"link":"/api/v1/people/605141","primaryPosition":{"code":"4","name":"Second Base","type":"Infielder","abbreviation":"2B"}}},{"id":"AFLRS","name":"AFL Rising Stars","date":"2013-11-03","season":"2013","team":{"id":542,"link":"/api/v1/teams/542","teamName":"Surprise"},"player":{"id":605141,"link":"/api/v1/people/605141","primaryPosition":{"code":"4","name":"Second Base","type":"Infielder","abbreviation":"2B"}}},{"id":"EASPOWH","name":"EAS Player of the Week","date":"2014-04-14","season":"2014","team":{"id":546,"link":"/api/v1/teams/546","teamName":"Portland"},"player":{"id":605141,"link":"/api/v1/people/605141","primaryPosition":{"code":"6","name":"Shortstop","type":"Infielder","abbreviation":"SS"}}},{"id":"FUTURES","name":"Futures Game Selection","date":"2014-07-13","season":"2014","team":{"id":533,"link":"/api/v1/teams/533","teamName":"Worcester"},"player":{"id":605141,"link":"/api/v1/people/605141","primaryPosition":{"code":"4","name":"Second Base","type":"Infielder","abbreviation":"2B"}}},{"id":"BAMILAS","name":"Baseball America Minor League All-Star","date":"2014-09-03","season":"2014","team":{"id":533,"link":"/api/v1/teams/533","teamName":"Worcester"},"player":{"id":605141,"link":"/api/v1/people/605141","primaryPosition":{"code":"9","name":"Outfielder","type":"Outfielder","abbreviation":"RF"}}},{"id":"BAMLART","name":"Baseball America Major League All-Rookie Team","date":"2014-10-05","season":"2014","team":{"id":111,"link":"/api/v1/teams/111","teamName":"Boston"},"player":{"id":605141,"link":"/api/v1/people/605141","primaryPosition":{"code":"4","name":"Second Base","type":"Infielder","abbreviation":"2B"}}},{"id":"MILBORGAS","name":"MiLB.com Organization All-Star","date":"2014-12-15","season":"2014","team":{"id":111,"link":"/api/v1/teams/111","teamName":"Boston"},"player":{"id":605141,"link":"/api/v1/people/605141","primaryPosition":{"code":"O","name":"Outfield","type":"Outfielder","abbreviation":"OF"}}},{"id":"ALPOW","name":"AL Player of the Week","date":"2015-06-22","season":"2015","team":{"id":111,"link":"/api/v1/teams/111","teamName":"Boston"},"player":{"id":605141,"link":"/api/v1/people/605141","primaryPosition":{"code":"8","name":"Outfielder","type":"Outfielder","abbreviation":"CF"}}},{"id":"BOSSPIRIT","name":"Red Sox Jensen Spirit Award","date":"2015-12-01","season":"2015","team":{"id":111,"link":"/api/v1/teams/111","teamName":"Boston"},"player":{"id":605141,"link":"/api/v1/people/605141","primaryPosition":{"code":"9","name":"Outfielder","type":"Outfielder","abbreviation":"RF"}}},{"id":"ALAS","name":"AL All-Star","date":"2016-07-12","season":"2016","team":{"id":111,"link":"/api/v1/teams/111","teamName":"Boston"},"player":{"id":605141,"link":"/api/v1/people/605141","primaryPosition":{"code":"9","name":"Outfielder","type":"Outfielder","abbreviation":"RF"}}},{"id":"ALPOM","name":"AL Player of the Month","date":"2016-07-31","season":"2016","team":{"id":111,"link":"/api/v1/teams/111","teamName":"Boston"},"player":{"id":605141,"link":"/api/v1/people/605141","primaryPosition":{"code":"8","name":"Outfielder","type":"Outfielder","abbreviation":"CF"}}},{"id":"ALGG","name":"Rawlings AL Gold Glove","date":"2016-11-08","season":"2016","team":{"id":111,"link":"/api/v1/teams/111","teamName":"Boston"},"player":{"id":605141,"link":"/api/v1/people/605141","primaryPosition":{"code":"9","name":"Outfielder","type":"Outfielder","abbreviation":"RF"}}},{"id":"ALSS","name":"AL Silver Slugger","date":"2016-11-10","season":"2016","team":{"id":111,"link":"/api/v1/teams/111","teamName":"Boston"},"player":{"id":605141,"link":"/api/v1/people/605141","primaryPosition":{"code":"O","name":"Outfield","type":"Outfielder","abbreviation":"OF"}}},{"id":"WDPOY","name":"Wilson Defensive Player of the Year","date":"2016-11-11","season":"2016","team":{"id":111,"link":"/api/v1/teams/111","teamName":"Boston"},"player":{"id":605141,"link":"/api/v1/people/605141","primaryPosition":{"code":"9","name":"Outfielder","type":"Outfielder","abbreviation":"RF"}}},{"id":"WMLBDPOY","name":"Wilson MLB Defensive Player of the Year","date":"2016-11-11","season":"2016","team":{"id":111,"link":"/api/v1/teams/111","teamName":"Boston"},"player":{"id":605141,"link":"/api/v1/people/605141","primaryPosition":{"code":"9","name":"Outfielder","type":"Outfielder","abbreviation":"RF"}}},{"id":"BOSMVP","name":"Thomas A. Yawkey Red Sox MVP","date":"2016-11-15","season":"2016","team":{"id":111,"link":"/api/v1/teams/111","teamName":"Boston"},"player":{"id":605141,"link":"/api/v1/people/605141","primaryPosition":{"code":"9","name":"Outfielder","type":"Outfielder","abbreviation":"RF"}}},{"id":"ALPOW","name":"AL Player of the Week","date":"2017-05-14","season":"2017","team":{"id":111,"link":"/api/v1/teams/111","teamName":"Boston"},"player":{"id":605141,"link":"/api/v1/people/605141","primaryPosition":{"code":"9","name":"Outfielder","type":"Outfielder","abbreviation":"RF"}}},{"id":"ALPOW","name":"AL Player of the Week","date":"2017-07-02","season":"2017","team":{"id":111,"link":"/api/v1/teams/111","teamName":"Boston"},"player":{"id":605141,"link":"/api/v1/people/605141","primaryPosition":{"code":"9","name":"Outfielder","type":"Outfielder","abbreviation":"RF"}}},{"id":"ALAS","name":"AL All-Star","date":"2017-07-11","season":"2017","team":{"id":111,"link":"/api/v1/teams/111","teamName":"Boston"},"player":{"id":605141,"link":"/api/v1/people/605141","primaryPosition":{"code":"9","name":"Outfielder","type":"Outfielder","abbreviation":"RF"}}},{"id":"ALGG","name":"Rawlings AL Gold Glove","date":"2017-11-07","season":"2017","team":{"id":111,"link":"/api/v1/teams/111","teamName":"Boston"},"player":{"id":605141,"link":"/api/v1/people/605141","primaryPosition":{"code":"9","name":"Outfielder","type":"Outfielder","abbreviation":"RF"}}},{"id":"BOSMVP","name":"Thomas A. Yawkey Red Sox MVP","date":"2017-11-15","season":"2017","team":{"id":111,"link":"/api/v1/teams/111","teamName":"Boston"},"player":{"id":605141,"link":"/api/v1/people/605141","primaryPosition":{"code":"9","name":"Outfielder","type":"Outfielder","abbreviation":"RF"}}},{"id":"ALAS","name":"AL All-Star","date":"2018-07-17","season":"2018","team":{"id":111,"link":"/api/v1/teams/111","teamName":"Boston"},"player":{"id":605141,"link":"/api/v1/people/605141","primaryPosition":{"code":"O","name":"Outfield","type":"Outfielder","abbreviation":"OF"}}},{"id":"BOSHEARTHUSTLE","name":"MLBPAA Red Sox Heart and Hustle Award","date":"2018-07-24","season":"2018","team":{"id":111,"link":"/api/v1/teams/111","teamName":"Boston"},"player":{"id":605141,"link":"/api/v1/people/605141","primaryPosition":{"code":"9","name":"Outfielder","type":"Outfielder","abbreviation":"RF"}}},{"id":"BOSMVP","name":"Thomas A. Yawkey Red Sox MVP","date":"2018-10-05","season":"2018","team":{"id":111,"link":"/api/v1/teams/111","teamName":"Boston"},"player":{"id":605141,"link":"/api/v1/people/605141","primaryPosition":{"code":"9","name":"Outfielder","type":"Outfielder","abbreviation":"RF"}}},{"id":"WSCHAMP","name":"World Series Championship","date":"2018-10-28","season":"2018","team":{"id":111,"link":"/api/v1/teams/111","teamName":"Boston"},"player":{"id":605141,"link":"/api/v1/people/605141","primaryPosition":{"code":"9","name":"Outfielder","type":"Outfielder","abbreviation":"RF"}}},{"id":"ALGG","name":"Rawlings AL Gold Glove","date":"2018-11-04","season":"2018","team":{"id":111,"link":"/api/v1/teams/111","teamName":"Boston"},"player":{"id":605141,"link":"/api/v1/people/605141","primaryPosition":{"code":"9","name":"Outfielder","type":"Outfielder","abbreviation":"RF"}}},{"id":"WDPOY","name":"Wilson Defensive Player of the Year","date":"2018-11-07","season":"2018","team":{"id":111,"link":"/api/v1/teams/111","teamName":"Boston"},"player":{"id":605141,"link":"/api/v1/people/605141","primaryPosition":{"code":"9","name":"Outfielder","type":"Outfielder","abbreviation":"RF"}}},{"id":"ALSS","name":"AL Silver Slugger","date":"2018-11-08","season":"2018","team":{"id":111,"link":"/api/v1/teams/111","teamName":"Boston"},"player":{"id":605141,"link":"/api/v1/people/605141","primaryPosition":{"code":"O","name":"Outfield","type":"Outfielder","abbreviation":"OF"}}},{"id":"HEARTANDHUSTLE","name":"MLBPAA Heart and Hustle Award","date":"2018-11-08","season":"2018","team":{"id":111,"link":"/api/v1/teams/111","teamName":"Boston"},"player":{"id":605141,"link":"/api/v1/people/605141","primaryPosition":{"code":"9","name":"Outfielder","type":"Outfielder","abbreviation":"RF"}}},{"id":"MLBPCALOP","name":"MLB Players Choice AL Outstanding Player","date":"2018-11-09","season":"2018","team":{"id":111,"link":"/api/v1/teams/111","teamName":"Boston"},"player":{"id":605141,"link":"/api/v1/people/605141","primaryPosition":{"code":"9","name":"Outfielder","type":"Outfielder","abbreviation":"RF"}}},{"id":"ALMVP","name":"AL MVP","date":"2018-11-15","season":"2018","team":{"id":111,"link":"/api/v1/teams/111","teamName":"Boston"},"player":{"id":605141,"link":"/api/v1/people/605141","primaryPosition":{"code":"O","name":"Outfield","type":"Outfielder","abbreviation":"OF"}}},{"id":"ALAS","name":"AL All-Star","date":"2019-07-09","season":"2019","team":{"id":111,"link":"/api/v1/teams/111","teamName":"Boston"},"player":{"id":605141,"link":"/api/v1/people/605141","primaryPosition":{"code":"O","name":"Outfield","type":"Outfielder","abbreviation":"OF"}}},{"id":"ALGG","name":"Rawlings AL Gold Glove","date":"2019-11-03","season":"2019","team":{"id":111,"link":"/api/v1/teams/111","teamName":"Boston"},"player":{"id":605141,"link":"/api/v1/people/605141","primaryPosition":{"code":"9","name":"Outfielder","type":"Outfielder","abbreviation":"RF"}}},{"id":"ALSS","name":"AL Silver Slugger","date":"2019-11-07","season":"2019","team":{"id":111,"link":"/api/v1/teams/111","teamName":"Boston"},"player":{"id":605141,"link":"/api/v1/people/605141","primaryPosition":{"code":"O","name":"Outfield","type":"Outfielder","abbreviation":"OF"}}},{"id":"MLBSECOND","name":"All-MLB Second Team","date":"2019-12-10","season":"2019","team":{"id":111,"link":"/api/v1/teams/111","teamName":"Boston"},"player":{"id":605141,"link":"/api/v1/people/605141","primaryPosition":{"code":"O","name":"Outfield","type":"Outfielder","abbreviation":"OF"}}},{"id":"MLBPLAYOW","name":"MLB Play of the Week","date":"2020-08-02","season":"2020","team":{"id":119,"link":"/api/v1/teams/119","teamName":"LA Dodgers"},"player":{"id":605141,"link":"/api/v1/people/605141","primaryPosition":{"code":"9","name":"Outfielder","type":"Outfielder","abbreviation":"RF"}}},{"id":"WSCHAMP","name":"World Series Championship","date":"2020-10-27","season":"2020","team":{"id":119,"link":"/api/v1/teams/119","teamName":"LA Dodgers"},"player":{"id":605141,"link":"/api/v1/people/605141","primaryPosition":{"code":"9","name":"Outfielder","type":"Outfielder","abbreviation":"RF"}}},{"id":"NLGG","name":"Rawlings NL Gold Glove","date":"2020-11-03","season":"2020","team":{"id":119,"link":"/api/v1/teams/119","teamName":"LA Dodgers"},"player":{"id":605141,"link":"/api/v1/people/605141","primaryPosition":{"code":"9","name":"Outfielder","type":"Outfielder","abbreviation":"RF"}}},{"id":"NLSS","name":"NL Silver Slugger","date":"2020-11-05","season":"2020","team":{"id":119,"link":"/api/v1/teams/119","teamName":"LA Dodgers"},"player":{"id":605141,"link":"/api/v1/people/605141","primaryPosition":{"code":"O","name":"Outfield","type":"Outfielder","abbreviation":"OF"}}},{"id":"MLBAFIRST","name":"All-MLB First Team","date":"2020-12-09","season":"2020","team":{"id":119,"link":"/api/v1/teams/119","teamName":"LA Dodgers"},"player":{"id":605141,"link":"/api/v1/people/605141","primaryPosition":{"code":"O","name":"Outfield","type":"Outfielder","abbreviation":"OF"}}},{"id":"MLBPLAYOW","name":"MLB Play of the Week","date":"2021-04-18","season":"2021","team":{"id":119,"link":"/api/v1/teams/119","teamName":"LA Dodgers"},"player":{"id":605141,"link":"/api/v1/people/605141","primaryPosition":{"code":"9","name":"Outfielder","type":"Outfielder","abbreviation":"RF"}}},{"id":"NLAS","name":"NL All-Star","date":"2021-07-13","season":"2021","team":{"id":119,"link":"/api/v1/teams/119","teamName":"LA Dodgers"},"player":{"id":605141,"link":"/api/v1/people/605141","primaryPosition":{"code":"O","name":"Outfield","type":"Outfielder","abbreviation":"OF"}}},{"id":"NLAS","name":"NL All-Star","date":"2022-07-19","season":"2022","team":{"id":119,"link":"/api/v1/teams/119","teamName":"LA Dodgers"},"player":{"id":605141,"link":"/api/v1/people/605141","primaryPosition":{"code":"O","name":"Outfield","type":"Outfielder","abbreviation":"OF"}}},{"id":"NLPOW","name":"NL Player of the Week","date":"2022-08-28","season":"2022","team":{"id":119,"link":"/api/v1/teams/119","teamName":"LA Dodgers"},"player":{"id":605141,"link":"/api/v1/people/605141","primaryPosition":{"code":"9","name":"Outfielder","type":"Outfielder","abbreviation":"RF"}}},{"id":"NLGG","name":"Rawlings NL Gold Glove","date":"2022-11-01","season":"2022","team":{"id":119,"link":"/api/v1/teams/119","teamName":"LA Dodgers"},"player":{"id":605141,"link":"/api/v1/people/605141","primaryPosition":{"code":"9","name":"Outfielder","type":"Outfielder","abbreviation":"RF"}}},{"id":"NLSS","name":"NL Silver Slugger","date":"2022-11-10","season":"2022","team":{"id":119,"link":"/api/v1/teams/119","teamName":"LA Dodgers"},"player":{"id":605141,"link":"/api/v1/people/605141","primaryPosition":{"code":"O","name":"Outfield","type":"Outfielder","abbreviation":"OF"}}},{"id":"MLBAFIRST","name":"All-MLB First Team","date":"2022-12-05","season":"2022","team":{"id":119,"link":"/api/v1/teams/119","teamName":"LA Dodgers"},"player":{"id":605141,"link":"/api/v1/people/605141","primaryPosition":{"code":"O","name":"Outfield","type":"Outfielder","abbreviation":"OF"}}},{"id":"HRDERBY","name":"Home Run Derby Participant","date":"2023-07-10","season":"2023","team":{"id":119,"link":"/api/v1/teams/119","teamName":"LA Dodgers"},"player":{"id":605141,"link":"/api/v1/people/605141","primaryPosition":{"code":"9","name":"Outfielder","type":"Outfielder","abbreviation":"RF"}}},{"id":"NLAS","name":"NL All-Star","date":"2023-07-11","season":"2023","team":{"id":119,"link":"/api/v1/teams/119","teamName":"LA Dodgers"},"player":{"id":605141,"link":"/api/v1/people/605141","primaryPosition":{"code":"O","name":"Outfield","type":"Outfielder","abbreviation":"OF"}}},{"id":"NLPOW","name":"NL Player of the Week","date":"2023-08-27","season":"2023","team":{"id":119,"link":"/api/v1/teams/119","teamName":"LA Dodgers"},"player":{"id":605141,"link":"/api/v1/people/605141","primaryPosition":{"code":"9","name":"Outfielder","type":"Outfielder","abbreviation":"RF"}}},{"id":"NLPOM","name":"NL Player of the Month","date":"2023-08-31","season":"2023","team":{"id":119,"link":"/api/v1/teams/119","teamName":"LA Dodgers"},"player":{"id":605141,"link":"/api/v1/people/605141","primaryPosition":{"code":"9","name":"Outfielder","type":"Outfielder","abbreviation":"RF"}}},{"id":"NLSS","name":"NL Silver Slugger","date":"2023-11-09","season":"2023","team":{"id":119,"link":"/api/v1/teams/119","teamName":"LA Dodgers"},"player":{"id":605141,"link":"/api/v1/people/605141","primaryPosition":{"code":"O","name":"Outfield","type":"Outfielder","abbreviation":"OF"}}},{"id":"MLBAFIRST","name":"All-MLB First Team","date":"2023-12-16","season":"2023","team":{"id":119,"link":"/api/v1/teams/119","teamName":"LA Dodgers"},"player":{"id":605141,"link":"/api/v1/people/605141","primaryPosition":{"code":"O","name":"Outfield","type":"Outfielder","abbreviation":"OF"}}},{"id":"NLPOM","name":"NL Player of the Month","date":"2024-04-30","season":"2024","team":{"id":119,"link":"/api/v1/teams/119","teamName":"LA Dodgers"},"player":{"id":605141,"link":"/api/v1/people/605141","primaryPosition":{"code":"9","name":"Outfielder","type":"Outfielder","abbreviation":"RF"}}},{"id":"NLAS","name":"NL All-Star","date":"2024-07-16","season":"2024","team":{"id":119,"link":"/api/v1/teams/119","teamName":"LA Dodgers"},"player":{"id":605141,"link":"/api/v1/people/605141","primaryPosition":{"code":"6","name":"Shortstop","type":"Infielder","abbreviation":"SS"}}},{"id":"WSCHAMP","name":"World Series Championship","date":"2024-10-30","season":"2024","team":{"id":119,"link":"/api/v1/teams/119","teamName":"LA Dodgers"},"player":{"id":605141,"link":"/api/v1/people/605141","primaryPosition":{"code":"6","name":"Shortstop","type":"Infielder","abbreviation":"SS"}}},{"id":"NLSS","name":"NL Silver Slugger","date":"2024-11-12","season":"2024","team":{"id":119,"link":"/api/v1/teams/119","teamName":"LA Dodgers"},"player":{"id":605141,"link":"/api/v1/people/605141","primaryPosition":{"code":"U","name":"Utility","type":"Infielder","abbreviation":"UT"}}},{"id":"MLBAFIRST","name":"All-MLB First Team","date":"2024-11-14","season":"2024","team":{"id":119,"link":"/api/v1/teams/119","teamName":"LA Dodgers"},"player":{"id":605141,"link":"/api/v1/people/605141","primaryPosition":{"code":"O","name":"Outfield","type":"Outfielder","abbreviation":"OF"}}},{"id":"BABERUTH","name":"Babe Ruth Award","date":"2024-12-04","season":"2024","team":{"id":119,"link":"/api/v1/teams/119","teamName":"LA Dodgers"},"player":{"id":605141,"link":"/api/v1/people/605141","primaryPosition":{"code":"9","name":"Outfielder","type":"Outfielder","abbreviation":"RF"}}},{"id":"NLPOW","name":"NL Player of the Week","date":"2025-09-14","season":"2025","team":{"id":119,"link":"/api/v1/teams/119","teamName":"LA Dodgers"},"player":{"id":605141,"link":"/api/v1/people/605141","primaryPosition":{"code":"6","name":"Shortstop","type":"Infielder","abbreviation":"SS"}}},{"id":"MLBRC","name":"Roberto Clemente Award","date":"2025-10-27","season":"2025","team":{"id":119,"link":"/api/v1/teams/119","teamName":"LA Dodgers"},"player":{"id":605141,"link":"/api/v1/people/605141","primaryPosition":{"code":"6","name":"Shortstop","type":"Infielder","abbreviation":"SS"}}},{"id":"WSCHAMP","name":"World Series Championship","date":"2025-11-01","season":"2025","team":{"id":119,"link":"/api/v1/teams/119","teamName":"LA Dodgers"},"player":{"id":605141,"link":"/api/v1/people/605141","primaryPosition":{"code":"6","name":"Shortstop","type":"Infielder","abbreviation":"SS"}}}]}